note_python-2.1.4.dist-info/licenses/LICENSE
notecard/__init__.py
notecard/binary_helpers.py
notecard/card.py
notecard/cobs.py
notecard/crc32.py
notecard/dfu.py
notecard/env.py
notecard/file.py
notecard/gpio.py
notecard/hub.py
notecard/md5.py
notecard/note.py
notecard/notecard.py
notecard/ntn.py
notecard/timeout.py
notecard/transaction_manager.py
notecard/validators.py
notecard/var.py
notecard/web.py
note_python-2.1.4.dist-info/METADATA
note_python-2.1.4.dist-info/WHEEL
note_python-2.1.4.dist-info/top_level.txt
note_python-2.1.4.dist-info/RECORD
