Metadata-Version: 2.4
Name: note-python
Version: 2.1.4
Summary: Cross-platform Python Library for the Blues Wireless Notecard
Author-email: "Blues Inc." <support@blues.com>
License: MIT
Project-URL: Homepage, https://github.com/blues/note-python
Project-URL: Repository, https://github.com/blues/note-python
Classifier: Programming Language :: Python
Classifier: Programming Language :: Python :: 3.9
Classifier: Programming Language :: Python :: 3.10
Classifier: Programming Language :: Python :: 3.11
Classifier: Programming Language :: Python :: 3.12
Classifier: Programming Language :: Python :: 3.13
Classifier: License :: OSI Approved :: MIT License
Classifier: Operating System :: OS Independent
Classifier: Intended Audience :: Developers
Classifier: Natural Language :: English
Requires-Python: >=3.9
License-File: LICENSE
Requires-Dist: filelock==3.0.12
Dynamic: license-file
